[
    {
        "id": 8867,
        "title": "Epic: 7.06-Oz Conchita Maria Cookies (Chocolate) $1.20 ",
        "category": "Tech",
        "source": "Slickdeals",
        "price": "Check Site",
        "originalPrice": "---",
        "image": "https://images.unsplash.com/photo-1498049794561-7780e7231661?auto=format&fit=crop&w=1350&q=80",
        "link": "https://www.amazon.com/Conchita-C...r=8-8&amp;th=1?tag=bigterry20036-20",
        "badge": "NEW"
    },
    {
        "id": 9201,
        "title": "Must-Have: Apple AirPods 4 Wireless Earbuds w/ USB-C Charging Case (w/o ANC) $89 + Free Shipping",
        "category": "Tech",
        "source": "Slickdeals",
        "price": "Check Site",
        "originalPrice": "---",
        "image": "https://images.unsplash.com/photo-1523275335684-37898b6baf30?auto=format&fit=crop&w=1350&q=80",
        "link": "https://slickdeals.net/f/19266088-89-00-apple-airpods-4-at-walmart?utm_source=rss&utm_content=fp&utm_medium=RSS2&ref=money_maker_2026",
        "badge": "NEW"
    },
    {
        "id": 1421,
        "title": "Must-Have: Slickdeals Daily Draw Giveaway \u2013 Enter Now for a Chance to Win! (See Official Rules) ",
        "category": "Tech",
        "source": "Slickdeals",
        "price": "Check Site",
        "originalPrice": "---",
        "image": "https://images.unsplash.com/photo-1498049794561-7780e7231661?auto=format&fit=crop&w=1350&q=80",
        "link": "https://slickdeals.net/f/18822175-slickdeals-daily-draw-giveaway-enter-now-for-a-chance-to-win-see-official-rules?utm_source=rss&utm_content=fp&utm_medium=RSS2&ref=money_maker_2026",
        "badge": "NEW"
    },
    {
        "id": 4231,
        "title": "Epic: Costco Members: Anker Nano 7-in-1 up to 100W Charging Station $54 + Free Shipping",
        "category": "Tech",
        "source": "Slickdeals",
        "price": "Check Site",
        "originalPrice": "---",
        "image": "https://images.unsplash.com/photo-1550751827-4bd374c3f58b?auto=format&fit=crop&w=1350&q=80",
        "link": "https://slickdeals.net/f/19264879-costco-members-anker-nano-7-in-1-up-to-100w-charging-station-54-free-shipping?utm_source=rss&utm_content=fp&utm_medium=RSS2&ref=money_maker_2026",
        "badge": "NEW"
    },
    {
        "id": 4118,
        "title": "Premium: 2-Pack Aukey MixFlex Sling 10,000mAh 30W PD USB-C Power Banks w/ Fold Out Plugs $30 + Free S/H",
        "category": "Tech",
        "source": "Slickdeals",
        "price": "Check Site",
        "originalPrice": "---",
        "image": "https://images.unsplash.com/photo-1550751827-4bd374c3f58b?auto=format&fit=crop&w=1350&q=80",
        "link": "https://slickdeals.net/f/19266433-2-pack-aukey-mixflex-sling-30w-pd-10-000mah-power-banks?utm_source=rss&utm_content=fp&utm_medium=RSS2&ref=money_maker_2026",
        "badge": "NEW"
    },
    {
        "id": 7767,
        "title": "Viral: JOYROOM Bluetooth 5.4 FM Transmitter + 45W PD & 36W QC 3.0 USB C Car Charger from $9.50 ",
        "category": "Tech",
        "source": "Slickdeals",
        "price": "Check Site",
        "originalPrice": "---",
        "image": "https://images.unsplash.com/photo-1523275335684-37898b6baf30?auto=format&fit=crop&w=1350&q=80",
        "link": "https://slickdeals.net/f/19252741-joyroom-bluetooth-5-4-fm-transmitter-45w-pd-36w-qc-3-0-usb-c-car-charger-black-9-49-more-free-shipping-w-prime-or-on-35?utm_source=rss&utm_content=fp&utm_medium=RSS2&ref=money_maker_2026",
        "badge": "NEW"
    },
    {
        "id": 8954,
        "title": "Insane: Anker GaN Prime 6-Port up to 250W USB-C Charging Station w/ 2.26\" Display $100 + Free Shipping",
        "category": "Tech",
        "source": "Slickdeals",
        "price": "Check Site",
        "originalPrice": "---",
        "image": "https://images.unsplash.com/photo-1523275335684-37898b6baf30?auto=format&fit=crop&w=1350&q=80",
        "link": "https://slickdeals.net/f/19263247-99-98-anker-gan-prime-6-port-up-to-250w-usb-c-charging-station-w-2-26-display-at-amazon?utm_source=rss&utm_content=fp&utm_medium=RSS2&ref=money_maker_2026",
        "badge": "NEW"
    },
    {
        "id": 2496,
        "title": "Viral: Patagonia Men's or Women's Nano Puff Insulated Jacket (Various) $113.85 + Free Shipping",
        "category": "Tech",
        "source": "Slickdeals",
        "price": "Check Site",
        "originalPrice": "---",
        "image": "https://images.unsplash.com/photo-1523275335684-37898b6baf30?auto=format&fit=crop&w=1350&q=80",
        "link": "https://slickdeals.net/f/19267150-patagonia-men-s-or-women-s-nano-puff-insulated-jacket-various-113-83-free-shipping?utm_source=rss&utm_content=fp&utm_medium=RSS2&ref=money_maker_2026",
        "badge": "NEW"
    },
    {
        "id": 6134,
        "title": "Insane: Skechers Men's USA Pollard Wilfred Dual Gore Moc Toe Slip-Ins Loafers (Taupe) $36 + Free Shipping",
        "category": "Tech",
        "source": "Slickdeals",
        "price": "Check Site",
        "originalPrice": "---",
        "image": "https://images.unsplash.com/photo-1550751827-4bd374c3f58b?auto=format&fit=crop&w=1350&q=80",
        "link": "https://www.amazon.com/Skechers-M...th=1&amp;psc=1?tag=bigterry20036-20",
        "badge": "NEW"
    },
    {
        "id": 5694,
        "title": "Exclusive: Soothfeel Men's Fleece Joggers Cotton Sweatpants (various colors) $10 ",
        "category": "Tech",
        "source": "Slickdeals",
        "price": "Check Site",
        "originalPrice": "---",
        "image": "https://images.unsplash.com/photo-1498049794561-7780e7231661?auto=format&fit=crop&w=1350&q=80",
        "link": "https://slickdeals.net/f/19263865-soothfeel-men-s-fleece-joggers-cotton-sweatpants-various-9-99?utm_source=rss&utm_content=fp&utm_medium=RSS2&ref=money_maker_2026",
        "badge": "NEW"
    },
    {
        "id": 9782,
        "title": "Premium: Milwaukee M12 FUEL 12V Brushless Stubby 3/8\" Impact Wrench w/ M12 XC HO 5Ah Battery $210 + Free Shipping",
        "category": "Tech",
        "source": "Slickdeals",
        "price": "Check Site",
        "originalPrice": "---",
        "image": "https://images.unsplash.com/photo-1523275335684-37898b6baf30?auto=format&fit=crop&w=1350&q=80",
        "link": "https://www.homedepot.com/p/Milwa.../331963332?ref=money_maker_2026",
        "badge": "NEW"
    },
    {
        "id": 7791,
        "title": "Insane: Refurbished Linksys MX5503 Atlas Pro 6 AX5400 Wi-Fi 6 Dual-Band Mesh System (3-Pack) $35 + Free S/H w/ Amazon Prime",
        "category": "Tech",
        "source": "Slickdeals",
        "price": "Check Site",
        "originalPrice": "---",
        "image": "https://images.unsplash.com/photo-1498049794561-7780e7231661?auto=format&fit=crop&w=1350&q=80",
        "link": "https://computers.woot.com/offers...cnt_wp_0_9?ref=money_maker_2026",
        "badge": "NEW"
    },
    {
        "id": 1608,
        "title": "Viral: DeWALT 12\" 15-Amp Dual Bevel Sliding Compound Corded Miter Saw (Tool Only) $399 + Free S/H",
        "category": "Tech",
        "source": "Slickdeals",
        "price": "Check Site",
        "originalPrice": "---",
        "image": "https://images.unsplash.com/photo-1550751827-4bd374c3f58b?auto=format&fit=crop&w=1350&q=80",
        "link": "https://slickdeals.net/f/19266850-dewalt-12-in-15-amp-dual-bevel-sliding-compound-corded-miter-saw-stainless-steel-one-size-dws780-399?utm_source=rss&utm_content=fp&utm_medium=RSS2&ref=money_maker_2026",
        "badge": "NEW"
    },
    {
        "id": 3253,
        "title": "Epic: 12-Pack Art3d 19.7\" x 19.7\" City Wall Panel (Black) $22.10 ",
        "category": "Tech",
        "source": "Slickdeals",
        "price": "Check Site",
        "originalPrice": "---",
        "image": "https://images.unsplash.com/photo-1523275335684-37898b6baf30?auto=format&fit=crop&w=1350&q=80",
        "link": "https://slickdeals.net/f/19265308-12-pack-art3d-19-7-x-19-7-wall-panel-black-22-10-free-shipping-w-prime-or-on-35?utm_source=rss&utm_content=fp&utm_medium=RSS2&ref=money_maker_2026",
        "badge": "NEW"
    },
    {
        "id": 9844,
        "title": "Insane: 49\" Acer Nitro UltraWide DQHD 5120x1440 1000R 32:9 Curved 240Hz 3ms Gaming Monitor $600 + Free Shipping",
        "category": "Tech",
        "source": "Slickdeals",
        "price": "Check Site",
        "originalPrice": "---",
        "image": "https://images.unsplash.com/photo-1518770660439-4636190af475?auto=format&fit=crop&w=1350&q=80",
        "link": "https://slickdeals.net/f/19264750-599-99-49-acer-acer-nitro-49-gaming-monitor-ultrawide-dqhd-5120-x-1440-1000r-32-9-curved-240hz-3ms-at-amazon?utm_source=rss&utm_content=fp&utm_medium=RSS2&ref=money_maker_2026",
        "badge": "NEW"
    },
    {
        "id": 1567,
        "title": "Premium: 2-Pack 6' Anker USB-A to USB-C 15W Charging Braided Cable (Black) $7 ",
        "category": "Tech",
        "source": "Slickdeals",
        "price": "Check Site",
        "originalPrice": "---",
        "image": "https://images.unsplash.com/photo-1498049794561-7780e7231661?auto=format&fit=crop&w=1350&q=80",
        "link": "https://slickdeals.net/f/19264669-2-pack-6-anker-usb-a-to-usb-c-15w-braided-charger-cables-black-7-free-shipping-w-prime-or-35-orders?utm_source=rss&utm_content=fp&utm_medium=RSS2&ref=money_maker_2026",
        "badge": "NEW"
    },
    {
        "id": 6510,
        "title": "Exclusive: 12-Pack TECKNET Solar Dusk to Dawn Fence Lights Outdoor $25.60 + Free Shipping",
        "category": "Tech",
        "source": "Slickdeals",
        "price": "Check Site",
        "originalPrice": "---",
        "image": "https://images.unsplash.com/photo-1518770660439-4636190af475?auto=format&fit=crop&w=1350&q=80",
        "link": "https://slickdeals.net/f/19265038-12-pack-tecknet-solar-dusk-to-dawn-fence-lights-outdoor-25-59-free-shipping-w-prime-or-on-35?utm_source=rss&utm_content=fp&utm_medium=RSS2&ref=money_maker_2026",
        "badge": "NEW"
    },
    {
        "id": 3793,
        "title": "Viral: Perfect Blue: Collector's Edition (4K UHD Blu-ray) $66.85 + Free Shipping",
        "category": "Tech",
        "source": "Slickdeals",
        "price": "Check Site",
        "originalPrice": "---",
        "image": "https://images.unsplash.com/photo-1550751827-4bd374c3f58b?auto=format&fit=crop&w=1350&q=80",
        "link": "https://slickdeals.net/f/19264918-perfect-blue-collector-s-edition-4k-uhd-66-84-free-shipping?utm_source=rss&utm_content=fp&utm_medium=RSS2&ref=money_maker_2026",
        "badge": "NEW"
    },
    {
        "id": 7320,
        "title": "Insane: 2-Pack UKCSIS up to 140W 3-Port GaN Foldable Wall Charger (USB-C, 2x USB-A) $19 + Free Shipping",
        "category": "Tech",
        "source": "Slickdeals",
        "price": "Check Site",
        "originalPrice": "---",
        "image": "https://images.unsplash.com/photo-1518770660439-4636190af475?auto=format&fit=crop&w=1350&q=80",
        "link": "https://slickdeals.net/f/19266244-2-pack-ukcsis-up-to-140w-3-port-gan-foldable-wall-charger-usb-c-2x-usb-a-18-99-free-shipping-w-prime-or-on-35?utm_source=rss&utm_content=fp&utm_medium=RSS2&ref=money_maker_2026",
        "badge": "NEW"
    },
    {
        "id": 4526,
        "title": "Must-Have: 12-Oz DeLallo Red Roasted Garlic Peppers $2.85 ",
        "category": "Tech",
        "source": "Slickdeals",
        "price": "Check Site",
        "originalPrice": "---",
        "image": "https://images.unsplash.com/photo-1498049794561-7780e7231661?auto=format&fit=crop&w=1350&q=80",
        "link": "https://slickdeals.net/f/19266967-12-oz-delallo-red-roasted-garlic-peppers-2-85-free-shipping-w-prime-or-on-35?utm_source=rss&utm_content=fp&utm_medium=RSS2&ref=money_maker_2026",
        "badge": "NEW"
    },
    {
        "id": 9984,
        "title": "Viral: 12-Oz Stanley Perfect Brew Stainless Steel Pour Over Camp Mug w/ Lid (Various) from $24.05 ",
        "category": "Tech",
        "source": "Slickdeals",
        "price": "Check Site",
        "originalPrice": "---",
        "image": "https://images.unsplash.com/photo-1498049794561-7780e7231661?auto=format&fit=crop&w=1350&q=80",
        "link": "https://slickdeals.net/f/19266289-12-ounce-stanley-perfect-brew-stainless-steel-pour-over-camp-mug-w-lid-cream-gloss-24-73-hammertone-green-27-63-more-free-shipping-w-prime-or-on-35?utm_source=rss&utm_content=fp&utm_medium=RSS2&ref=money_maker_2026",
        "badge": "NEW"
    },
    {
        "id": 5300,
        "title": "Unbeatable: Select Amazon Accounts: 16oz. Amazon Saver Original Saltine Crackers $1.55 ",
        "category": "Tech",
        "source": "Slickdeals",
        "price": "Check Site",
        "originalPrice": "---",
        "image": "https://images.unsplash.com/photo-1550751827-4bd374c3f58b?auto=format&fit=crop&w=1350&q=80",
        "link": "https://www.amazon.com/Amazon-Bra...07WSTZ95G/?tag=bigterry20036-20",
        "badge": "NEW"
    },
    {
        "id": 7434,
        "title": "Epic: Milk Street 365: The All-Purpose Cookbook for Every Day of the Year (eBook) $2 ",
        "category": "Tech",
        "source": "Slickdeals",
        "price": "Check Site",
        "originalPrice": "---",
        "image": "https://images.unsplash.com/photo-1518770660439-4636190af475?auto=format&fit=crop&w=1350&q=80",
        "link": "https://www.amazon.com/dp/B0CDWL5G9J?tag=bigterry20036-20",
        "badge": "NEW"
    },
    {
        "id": 8895,
        "title": "Must-Have: Little Tikes Easy Store Jr. Picnic Play Table w/ Umbrella $40.60 + Free Shipping & More",
        "category": "Tech",
        "source": "Slickdeals",
        "price": "Check Site",
        "originalPrice": "---",
        "image": "https://images.unsplash.com/photo-1550751827-4bd374c3f58b?auto=format&fit=crop&w=1350&q=80",
        "link": "https://slickdeals.net/f/19264282-little-tikes-easy-store-jr-picnic-play-table-w-umbrella-blue-green-40-59-free-shipping?utm_source=rss&utm_content=fp&utm_medium=RSS2&ref=money_maker_2026",
        "badge": "NEW"
    },
    {
        "id": 9508,
        "title": "Premium: Just Move: Clean City Messy Battle (PC Digital Download) Free ",
        "category": "Tech",
        "source": "Slickdeals",
        "price": "Check Site",
        "originalPrice": "---",
        "image": "https://images.unsplash.com/photo-1523275335684-37898b6baf30?auto=format&fit=crop&w=1350&q=80",
        "link": "https://slickdeals.net/f/19263301-just-move-clean-city-messy-battle-pc-digital-download-free?utm_source=rss&utm_content=fp&utm_medium=RSS2&ref=money_maker_2026",
        "badge": "NEW"
    },
    {
        "id": 8997,
        "title": "Premium: VibeLens MusicCam Bone Conduction Headphones for $200 + free shipping",
        "category": "Tech",
        "source": "DealNews Tech",
        "price": "Check Site",
        "originalPrice": "---",
        "image": "https://www.datocms-assets.com/64599/1772550199-619jxypqy1l-ac_sl1500.jpg?h=119&w=125",
        "link": "https://www.dealnews.com/Vibe-Lens-Music-Cam-Bone-Conduction-Headphones-for-200-free-shipping/21813810.html?iref=rss-c142&ref=money_maker_2026",
        "badge": "NEW"
    },
    {
        "id": 2480,
        "title": "Epic: Developers Project Starter Kit for Uno R3 for $13 + free shipping w/ first order",
        "category": "Tech",
        "source": "DealNews Tech",
        "price": "Check Site",
        "originalPrice": "---",
        "image": "https://www.datocms-assets.com/64599/1772547241-uno-r3-super-starter-kit-overhead-y8qe.avif?h=125&w=125",
        "link": "https://www.dealnews.com/Developers-Project-Starter-Kit-for-Uno-R3-for-13-free-shipping-w-first-order/21813772.html?iref=rss-c142&ref=money_maker_2026",
        "badge": "NEW"
    },
    {
        "id": 4377,
        "title": "Must-Have: Onn 65\" 4K HDR LED UHD Smart TV for $217 + free shipping",
        "category": "Tech",
        "source": "DealNews Tech",
        "price": "Check Site",
        "originalPrice": "---",
        "image": "https://www.datocms-assets.com/64599/1701907816-dn-image-7543862.jpg?h=82&w=125",
        "link": "https://www.dealnews.com/products/Onn/Onn-65-4-K-HDR-LED-UHD-Smart-TV/363527.html?iref=rss-c142&ref=money_maker_2026",
        "badge": "NEW"
    },
    {
        "id": 8242,
        "title": "Premium: OtterBox iPhone 16 Pro Max Statement Series Cactus Leather Case  for $7 + free shipping w/ Prime",
        "category": "Tech",
        "source": "DealNews Tech",
        "price": "Check Site",
        "originalPrice": "---",
        "image": "https://www.datocms-assets.com/64599/1772535888-dark-blue-phone-case-back-view-7rcr.png?h=125&w=77",
        "link": "https://www.dealnews.com/Otter-Box-iPhone-16-Pro-Max-Statement-Series-Cactus-Leather-Case-for-7-free-shipping-w-Prime/21813734.html?iref=rss-c142&ref=money_maker_2026",
        "badge": "NEW"
    },
    {
        "id": 7853,
        "title": "Insane: Portable Charger & Power Bank Deals at Best Buy: Up to 70% off + free shipping",
        "category": "Tech",
        "source": "DealNews Tech",
        "price": "Check Site",
        "originalPrice": "---",
        "image": "https://www.datocms-assets.com/64599/1772534391-anker-portable-charger-usb-c-bzz9.avif?h=125&w=96",
        "link": "https://www.dealnews.com/Portable-Charger-Power-Bank-Deals-at-Best-Buy-Up-to-70-off-free-shipping/21813730.html?iref=rss-c142&ref=money_maker_2026",
        "badge": "NEW"
    },
    {
        "id": 5239,
        "title": "Epic: 140W USB C 3-Port Multi-Device Fast Power Adapter 2-Pack for $19 + free shipping w/ Prime",
        "category": "Tech",
        "source": "DealNews Tech",
        "price": "Check Site",
        "originalPrice": "---",
        "image": "https://www.datocms-assets.com/64599/1772526105-ukcsis-140w-gan-usb-wall-charger-pygb.jpeg?h=99&w=125",
        "link": "https://www.dealnews.com/140-W-USB-C-3-Port-Multi-Device-Fast-Power-Adapter-2-Pack-for-19-free-shipping-w-Prime/21813701.html?iref=rss-c142&ref=money_maker_2026",
        "badge": "NEW"
    },
    {
        "id": 7346,
        "title": "Must-Have: Anker PowerPort PD 60W GaN Fast Charger for $23 + free shipping",
        "category": "Tech",
        "source": "DealNews Tech",
        "price": "Check Site",
        "originalPrice": "---",
        "image": "https://www.datocms-assets.com/64599/1770889111-anker-usb-wall-charger-dual-ports-3cbe.avif?h=104&w=125",
        "link": "https://www.dealnews.com/Anker-Power-Port-PD-60-W-Ga-N-Fast-Charger-for-23-free-shipping/21813695.html?iref=rss-c142&ref=money_maker_2026",
        "badge": "NEW"
    },
    {
        "id": 3295,
        "title": "Premium: Obsbot Me AI Powered Auto Tracking Tripod Phone Mount for $50 + free shipping",
        "category": "Tech",
        "source": "DealNews Tech",
        "price": "Check Site",
        "originalPrice": "---",
        "image": "https://www.datocms-assets.com/64599/1772523068-obsbot-smartphone-gimbal-camera-lmez.avif?h=125&w=66",
        "link": "https://www.dealnews.com/Obsbot-Me-AI-Powered-Auto-Tracking-Tripod-Phone-Mount-for-50-free-shipping/21813694.html?iref=rss-c142&ref=money_maker_2026",
        "badge": "NEW"
    },
    {
        "id": 2799,
        "title": "Viral: Amazon Renewed Phones: Get Deals on Apple, Samsung + free shipping",
        "category": "Tech",
        "source": "DealNews Tech",
        "price": "Check Site",
        "originalPrice": "---",
        "image": "https://www.datocms-assets.com/64599/1772492241-dark-gray-apple-smartphone-hqvh.avif?h=125&w=125",
        "link": "https://www.dealnews.com/Amazon-Renewed-Phones-Get-Deals-on-Apple-Samsung-free-shipping/21813664.html?iref=rss-c142&ref=money_maker_2026",
        "badge": "NEW"
    },
    {
        "id": 8089,
        "title": "Unbeatable: Mint Mobile All Unlimited Plans for $15 per month",
        "category": "Tech",
        "source": "DealNews Tech",
        "price": "Check Site",
        "originalPrice": "---",
        "image": "https://www.datocms-assets.com/64599/1772439460-mint-mobile-logo-otm0.webp?h=125&w=125",
        "link": "https://www.dealnews.com/Mint-Mobile-All-Unlimited-Plans-for-15-per-month/21813395.html?iref=rss-c142&ref=money_maker_2026",
        "badge": "NEW"
    },
    {
        "id": 2633,
        "title": "Viral: Newegg March Madness Sale: Up to 60% off + free shipping",
        "category": "Tech",
        "source": "DealNews Tech",
        "price": "Check Site",
        "originalPrice": "---",
        "image": "https://www.datocms-assets.com/64599/1772490271-bitaxe-electronic-component-fan-bswq.webp?h=125&w=95",
        "link": "https://www.dealnews.com/Newegg-March-Madness-Sale-Up-to-60-off-free-shipping/21813659.html?iref=rss-c142&ref=money_maker_2026",
        "badge": "NEW"
    },
    {
        "id": 5688,
        "title": "Exclusive: Altec Lansing HydraBlast Portable Everything-Proof Speaker for $20 + free shipping",
        "category": "Tech",
        "source": "DealNews Tech",
        "price": "Check Site",
        "originalPrice": "---",
        "image": "https://www.datocms-assets.com/64599/1772482428-s-l1600-7.jpg?h=125&w=125",
        "link": "https://www.dealnews.com/products/Altec-Lansing/Altec-Lansing-Hydra-Blast-Portable-Everything-Proof-Speaker/497829.html?iref=rss-c142&ref=money_maker_2026",
        "badge": "NEW"
    },
    {
        "id": 2560,
        "title": "Exclusive: VIPOutlet Electronics Sale at eBay: Up to 67% off + extra 10% off + free shipping",
        "category": "Tech",
        "source": "DealNews Tech",
        "price": "Check Site",
        "originalPrice": "---",
        "image": "https://www.datocms-assets.com/64599/1772481874-s-l1600-3.png?h=56&w=125",
        "link": "https://www.dealnews.com/VIPOutlet-Electronics-Sale-at-eBay-Up-to-67-off-extra-10-off-free-shipping/21813621.html?iref=rss-c142&ref=money_maker_2026",
        "badge": "NEW"
    },
    {
        "id": 4979,
        "title": "Epic: Skullcandy Crusher Evo Wireless Bluetooth Headphones for $100 + free shipping",
        "category": "Tech",
        "source": "DealNews Tech",
        "price": "Check Site",
        "originalPrice": "---",
        "image": "https://www.datocms-assets.com/64599/1772481481-crusher.jpg?h=125&w=111",
        "link": "https://www.dealnews.com/products/Skullcandy/Skullcandy-Crusher-Evo-Wireless-Bluetooth-Headphones/497828.html?iref=rss-c142&ref=money_maker_2026",
        "badge": "NEW"
    },
    {
        "id": 2582,
        "title": "Epic: Surge Protector Power Strip w/ 6-Foot Cord for $14 + free shipping w/ Prime",
        "category": "Tech",
        "source": "DealNews Tech",
        "price": "Check Site",
        "originalPrice": "---",
        "image": "https://www.datocms-assets.com/64599/1772480750-strip.jpg?h=121&w=125",
        "link": "https://www.dealnews.com/Surge-Protector-Power-Strip-w-6-Foot-Cord-for-14-free-shipping-w-Prime/21813610.html?iref=rss-c142&ref=money_maker_2026",
        "badge": "NEW"
    },
    {
        "id": 5087,
        "title": "Exclusive: TZT FM-TX180 75MHz to 108MHz FM Radio Transmitter for $40.50 + free shipping w/ first order",
        "category": "Tech",
        "source": "DealNews Tech",
        "price": "Check Site",
        "originalPrice": "---",
        "image": "https://www.datocms-assets.com/64599/1772475844-white-fm-tx180-fm-transmitter-accessories-fqvw.avif?h=125&w=125",
        "link": "https://www.dealnews.com/TZT-FM-TX180-75-MHz-to-108-MHz-FM-Radio-Transmitter-for-40-50-free-shipping-w-first-order/21813584.html?iref=rss-c142&ref=money_maker_2026",
        "badge": "NEW"
    },
    {
        "id": 8725,
        "title": "Epic: Certified Refurb EcoFlow Delta Pro 3,600Wh Power Station + Extra 3,600Wh Battery for $1,899 + free shipping",
        "category": "Tech",
        "source": "DealNews Tech",
        "price": "Check Site",
        "originalPrice": "---",
        "image": "https://www.datocms-assets.com/64599/1772475293-2026-03-02_13-14-32.png?h=91&w=125",
        "link": "https://www.dealnews.com/Certified-Refurb-Eco-Flow-Delta-Pro-3-600-Wh-Power-Station-Extra-3-600-Wh-Battery-for-1-899-free-shipping/21813581.html?iref=rss-c142&ref=money_maker_2026",
        "badge": "NEW"
    },
    {
        "id": 2628,
        "title": "Insane: Topleo Android 14.0 TV Box for $11 + free shipping w/ first order",
        "category": "Tech",
        "source": "DealNews Tech",
        "price": "Check Site",
        "originalPrice": "---",
        "image": "https://www.datocms-assets.com/64599/1772474497-h605b8cbb71774a4e9b91d91a187a5c6fb.jpeg?h=125&w=125",
        "link": "https://www.dealnews.com/Topleo-Android-14-0-TV-Box-for-11-free-shipping-w-first-order/21813578.html?iref=rss-c142&ref=money_maker_2026",
        "badge": "NEW"
    },
    {
        "id": 6677,
        "title": "Viral: Amazon Fire TV Stick 4K Plus (2025) for $25 + free shipping w/ Prime",
        "category": "Tech",
        "source": "DealNews Tech",
        "price": "Check Site",
        "originalPrice": "---",
        "image": "https://www.datocms-assets.com/64599/1761940129-71na62xtltl-ac_sl1500.jpg?h=96&w=125",
        "link": "https://www.dealnews.com/products/Amazon/Amazon-Fire-TV-Stick-4-K-Plus-2025/495874.html?iref=rss-c142&ref=money_maker_2026",
        "badge": "NEW"
    },
    {
        "id": 3603,
        "title": "Exclusive: Apple iPhone 16e 128GB Smartphone for Metro by T-Mobile w/ $100 virtual prepaid Mastercard for $100 + free shipping",
        "category": "Tech",
        "source": "DealNews Tech",
        "price": "Check Site",
        "originalPrice": "---",
        "image": "https://www.datocms-assets.com/64599/1771834593-screenshot-2026-02-23-at-08-15-41.png?h=82&w=125",
        "link": "https://www.dealnews.com/Apple-iPhone-16-e-128-GB-Smartphone-for-Metro-by-T-Mobile-w-100-virtual-prepaid-Mastercard-for-100-free-shipping/21811845.html?iref=rss-c142&ref=money_maker_2026",
        "badge": "NEW"
    },
    {
        "id": 6531,
        "title": "Viral: Sumry HGX 4KW 24V 140A 5,600W Off-Grid Solar Inverter for $231 + free shipping",
        "category": "Tech",
        "source": "DealNews Tech",
        "price": "Check Site",
        "originalPrice": "---",
        "image": "https://www.datocms-assets.com/64599/1772468797-screenshot-2026-03-02-at-10-26-24-am.png?h=125&w=124",
        "link": "https://www.dealnews.com/Sumry-HGX-4-KW-24-V-140-A-5-600-W-Off-Grid-Solar-Inverter-for-231-free-shipping/21813546.html?iref=rss-c142&ref=money_maker_2026",
        "badge": "NEW"
    },
    {
        "id": 4426,
        "title": "Viral: Dell Alienware Aurora 16\" Intel Core 7 Gaming Laptop w/ NVIDIA GeForce RTX 5050 and 512GB SSD for $1,100 + free shipping",
        "category": "Tech",
        "source": "DealNews Home",
        "price": "Check Site",
        "originalPrice": "---",
        "image": "https://www.datocms-assets.com/64599/1772549192-dark-blue-alienware-gaming-laptop-a6dn.webp?h=125&w=125",
        "link": "https://www.dealnews.com/Dell-Alienware-Aurora-16-Intel-Core-7-Gaming-Laptop-w-NVIDIA-Ge-Force-RTX-5050-and-512-GB-SSD-for-1-100-free-shipping/21813785.html?iref=rss-c49&ref=money_maker_2026",
        "badge": "NEW"
    },
    {
        "id": 5781,
        "title": "Insane: Apple MacBook Air M1 13\" Laptop (2020) for $350 + free shipping",
        "category": "Tech",
        "source": "DealNews Home",
        "price": "Check Site",
        "originalPrice": "---",
        "image": "https://www.datocms-assets.com/64599/1702475777-dn-image-7785425.jpg?h=73&w=125",
        "link": "https://www.dealnews.com/products/Apple/Apple-Mac-Book-Air-M1-13-Laptop-2020/441925.html?iref=rss-c49&ref=money_maker_2026",
        "badge": "NEW"
    },
    {
        "id": 1397,
        "title": "Epic: Dell 16 Plus Core Ultra 7 258V 16\" Laptop w/ 32GB RAM & 1TB SSD for $1,000 + free shipping",
        "category": "Tech",
        "source": "DealNews Home",
        "price": "Check Site",
        "originalPrice": "---",
        "image": "https://www.datocms-assets.com/64599/1757949654-dell-laptop-silver-front-zuxf.avif?h=97&w=125",
        "link": "https://www.dealnews.com/products/Dell/Dell-16-Plus-Core-Ultra-7-258-V-16-Laptop-w-32-GB-RAM-1-TB-SSD/495449.html?iref=rss-c49&ref=money_maker_2026",
        "badge": "NEW"
    },
    {
        "id": 6584,
        "title": "Epic: Refurbished Dell Latitude 7440 Laptops: 50% off + free shipping",
        "category": "Tech",
        "source": "DealNews Home",
        "price": "Check Site",
        "originalPrice": "---",
        "image": "https://www.datocms-assets.com/64599/1772477799-dell-laptop-front-view-g5fa.jpeg?h=125&w=125",
        "link": "https://www.dealnews.com/Refurbished-Dell-Latitude-7440-Laptops-50-off-free-shipping/21813613.html?iref=rss-c49&ref=money_maker_2026",
        "badge": "NEW"
    }
]